{"adult":false,"backdrop_path":null,"belongs_to_collection":null,"budget":0,"genres":[{"id":16,"name":"Animaci\u00f3n"}],"homepage":"","id":1502489,"imdb_id":null,"origin_country":["US"],"original_language":"en","original_title":"K\/DA - POP\/STARS","overview":"","popularity":0.0825,"poster_path":"\/QWFZj521vQ8PrltH0LDk2pevYy.jpg","production_companies":[{"id":99496,"logo_path":"\/6WTCdsmIH6qR2zFVHlqjpIZhD5A.png","name":"Fortiche Production","origin_country":"FR"}],"production_countries":[{"iso_3166_1":"FR","name":"France"}],"release_date":"2018-11-03","revenue":0,"runtime":3,"spoken_languages":[],"status":"Released","tagline":"","title":"K\/DA - POP\/STARS","video":false,"vote_average":0,"vote_count":0}